{
  "config": "{\"version\":\"5.51\",\"themeCollection\":{\"baseTheme\":{\"name\":\"CY24SU02\",\"version\":\"5.51\",\"type\":2}},\"activeSectionIndex\":0,\"defaultDrillFilterOtherVisuals\":true,\"linguisticSchemaSyncVersion\":2,\"settings\":{\"useNewFilterPaneExperience\":true,\"allowChangeFilterTypes\":true,\"useStylableVisualContainerHeader\":true,\"queryLimitOption\":6,\"exportDataMode\":1,\"useDefaultAggregateDisplayName\":true},\"objects\":{\"section\":[{\"properties\":{\"verticalAlignment\":{\"expr\":{\"Literal\":{\"Value\":\"'Top'\"}}}}}]}}",
  "layoutOptimization": 0,
  "resourcePackages": [
    {
      "resourcePackage": {
        "disabled": false,
        "items": [
          {
            "name": "Background6747308397839318.png",
            "path": "Background6747308397839318.png",
            "type": 100
          }
        ],
        "name": "RegisteredResources",
        "type": 1
      }
    },
    {
      "resourcePackage": {
        "disabled": false,
        "items": [
          {
            "name": "CY24SU02",
            "path": "BaseThemes/CY24SU02.json",
            "type": 202
          }
        ],
        "name": "SharedResources",
        "type": 2
      }
    }
  ],
  "sections": [
    {
      "config": "{\"objects\":{\"background\":[{\"properties\":{\"image\":{\"image\":{\"name\":{\"expr\":{\"Literal\":{\"Value\":\"'Background.png'\"}}},\"url\":{\"expr\":{\"ResourcePackageItem\":{\"PackageName\":\"RegisteredResources\",\"PackageType\":1,\"ItemName\":\"Background6747308397839318.png\"}}},\"scaling\":{\"expr\":{\"Literal\":{\"Value\":\"'Normal'\"}}}}},\"transparency\":{\"expr\":{\"Literal\":{\"Value\":\"0D\"}}}}}]}}",
      "displayName": "Page 1",
      "displayOption": 1,
      "filters": "[]",
      "height": 1200.00,
      "name": "ReportSection",
      "visualContainers": [
        {
          "config": "{\"name\":\"08eddff4e91957dd61d8\",\"layouts\":[{\"id\":0,\"position\":{\"x\":236.51877133105802,\"y\":11.262798634812286,\"z\":6000,\"width\":542.6621160409557,\"height\":63.48122866894198,\"tabOrder\":7000}}],\"singleVisual\":{\"visualType\":\"textbox\",\"drillFilterOtherVisuals\":true,\"objects\":{\"general\":[{\"properties\":{\"paragraphs\":[{\"textRuns\":[{\"value\":\"New Zealand Motor Vehicle Thefts\",\"textStyle\":{\"fontFamily\":\"Segoe (Bold)\",\"fontSize\":\"24pt\",\"color\":\"#ffffff\"}}]}]}}]},\"vcObjects\":{\"background\":[{\"properties\":{\"show\":{\"expr\":{\"Literal\":{\"Value\":\"false\"}}}}}]}}}",
          "filters": "[]",
          "height": 63.48,
          "width": 542.66,
          "x": 236.52,
          "y": 11.26,
          "z": 6000.00
        },
        {
          "config": "{\"name\":\"21b948ddd5ae53a0985e\",\"layouts\":[{\"id\":0,\"position\":{\"x\":35.83617747440273,\"y\":622.5255972696245,\"z\":3000,\"width\":435.1535836177474,\"height\":265.1877133105802,\"tabOrder\":3000}}],\"singleVisual\":{\"visualType\":\"clusteredBarChart\",\"projections\":{\"Category\":[{\"queryRef\":\"stolen_vehicles.vehicle_type\",\"active\":true}],\"Y\":[{\"queryRef\":\"stolen_vehicles.Stolen Vehicles Count\"}]},\"prototypeQuery\":{\"Version\":2,\"From\":[{\"Name\":\"s\",\"Entity\":\"stolen_vehicles\",\"Type\":0}],\"Select\":[{\"Column\":{\"Expression\":{\"SourceRef\":{\"Source\":\"s\"}},\"Property\":\"vehicle_type\"},\"Name\":\"stolen_vehicles.vehicle_type\",\"NativeReferenceName\":\"vehicle_type\"},{\"Measure\":{\"Expression\":{\"SourceRef\":{\"Source\":\"s\"}},\"Property\":\"Stolen Vehicles Count\"},\"Name\":\"stolen_vehicles.Stolen Vehicles Count\",\"NativeReferenceName\":\"Stolen Vehicles Count\"}],\"OrderBy\":[{\"Direction\":2,\"Expression\":{\"Measure\":{\"Expression\":{\"SourceRef\":{\"Source\":\"s\"}},\"Property\":\"Stolen Vehicles Count\"}}}]},\"drillFilterOtherVisuals\":true,\"hasDefaultSort\":true,\"objects\":{\"labels\":[{\"properties\":{\"show\":{\"expr\":{\"Literal\":{\"Value\":\"true\"}}},\"labelPosition\":{\"expr\":{\"Literal\":{\"Value\":\"'InsideEnd'\"}}},\"fontFamily\":{\"expr\":{\"Literal\":{\"Value\":\"'''Segoe UI Semibold'', wf_segoe-ui_semibold, helvetica, arial, sans-serif'\"}}}}},{\"properties\":{\"color\":{\"solid\":{\"color\":{\"expr\":{\"ThemeDataColor\":{\"ColorId\":0,\"Percent\":0}}}}}},\"selector\":{\"data\":[{\"dataViewWildcard\":{\"matchingOption\":1}}]}}],\"valueAxis\":[{\"properties\":{\"showAxisTitle\":{\"expr\":{\"Literal\":{\"Value\":\"false\"}}},\"labelColor\":{\"solid\":{\"color\":{\"expr\":{\"ThemeDataColor\":{\"ColorId\":0,\"Percent\":0}}}}},\"gridlineShow\":{\"expr\":{\"Literal\":{\"Value\":\"false\"}}}}}],\"categoryAxis\":[{\"properties\":{\"show\":{\"expr\":{\"Literal\":{\"Value\":\"true\"}}},\"showAxisTitle\":{\"expr\":{\"Literal\":{\"Value\":\"false\"}}},\"labelColor\":{\"solid\":{\"color\":{\"expr\":{\"ThemeDataColor\":{\"ColorId\":0,\"Percent\":0}}}}},\"fontFamily\":{\"expr\":{\"Literal\":{\"Value\":\"'''Segoe UI Semibold'', wf_segoe-ui_semibold, helvetica, arial, sans-serif'\"}}}}}],\"legend\":[{\"properties\":{\"show\":{\"expr\":{\"Literal\":{\"Value\":\"false\"}}},\"showTitle\":{\"expr\":{\"Literal\":{\"Value\":\"false\"}}},\"labelColor\":{\"solid\":{\"color\":{\"expr\":{\"ThemeDataColor\":{\"ColorId\":0,\"Percent\":0}}}}},\"fontFamily\":{\"expr\":{\"Literal\":{\"Value\":\"'''Segoe UI Semibold'', wf_segoe-ui_semibold, helvetica, arial, sans-serif'\"}}},\"showGradientLegend\":{\"expr\":{\"Literal\":{\"Value\":\"false\"}}}}}],\"dataPoint\":[{\"properties\":{\"fill\":{\"solid\":{\"color\":{\"expr\":{\"FillRule\":{\"Input\":{\"Measure\":{\"Expression\":{\"SourceRef\":{\"Entity\":\"stolen_vehicles\"}},\"Property\":\"Stolen Vehicles Count\"}},\"FillRule\":{\"linearGradient2\":{\"min\":{\"color\":{\"Literal\":{\"Value\":\"'#B696F6'\"}}},\"max\":{\"color\":{\"Literal\":{\"Value\":\"'#9842ED'\"}}},\"nullColoringStrategy\":{\"strategy\":{\"Literal\":{\"Value\":\"'asZero'\"}}}}}}}}}}},\"selector\":{\"data\":[{\"dataViewWildcard\":{\"matchingOption\":1}}]}}]},\"vcObjects\":{\"title\":[{\"properties\":{\"text\":{\"expr\":{\"Literal\":{\"Value\":\"'Stolen Vehicles by Vehicle Type'\"}}},\"titleWrap\":{\"expr\":{\"Literal\":{\"Value\":\"true\"}}},\"fontColor\":{\"solid\":{\"color\":{\"expr\":{\"ThemeDataColor\":{\"ColorId\":0,\"Percent\":0}}}}},\"fontSize\":{\"expr\":{\"Literal\":{\"Value\":\"12D\"}}},\"fontFamily\":{\"expr\":{\"Literal\":{\"Value\":\"'''Segoe UI Semibold'', wf_segoe-ui_semibold, helvetica, arial, sans-serif'\"}}}}}],\"background\":[{\"properties\":{\"show\":{\"expr\":{\"Literal\":{\"Value\":\"false\"}}},\"transparency\":{\"expr\":{\"Literal\":{\"Value\":\"0D\"}}}}}]}}}",
          "filters": "[]",
          "height": 265.19,
          "width": 435.15,
          "x": 35.84,
          "y": 622.53,
          "z": 3000.00
        },
        {
          "config": "{\"name\":\"32390284175b0bb0779a\",\"layouts\":[{\"id\":0,\"position\":{\"x\":528.3276450511945,\"y\":100.34129692832764,\"z\":1000,\"width\":435.1535836177474,\"height\":244.7098976109215,\"tabOrder\":1000}}],\"singleVisual\":{\"visualType\":\"clusteredBarChart\",\"projections\":{\"Y\":[{\"queryRef\":\"stolen_vehicles.Stolen Vehicles Count\"}],\"Category\":[{\"queryRef\":\"make_details.make_name\",\"active\":true}]},\"prototypeQuery\":{\"Version\":2,\"From\":[{\"Name\":\"s\",\"Entity\":\"stolen_vehicles\",\"Type\":0},{\"Name\":\"m\",\"Entity\":\"make_details\",\"Type\":0}],\"Select\":[{\"Measure\":{\"Expression\":{\"SourceRef\":{\"Source\":\"s\"}},\"Property\":\"Stolen Vehicles Count\"},\"Name\":\"stolen_vehicles.Stolen Vehicles Count\",\"NativeReferenceName\":\"Stolen Vehicles Count1\"},{\"Column\":{\"Expression\":{\"SourceRef\":{\"Source\":\"m\"}},\"Property\":\"make_name\"},\"Name\":\"make_details.make_name\",\"NativeReferenceName\":\"make_name\"}],\"OrderBy\":[{\"Direction\":2,\"Expression\":{\"Measure\":{\"Expression\":{\"SourceRef\":{\"Source\":\"s\"}},\"Property\":\"Stolen Vehicles Count\"}}}]},\"drillFilterOtherVisuals\":true,\"hasDefaultSort\":true,\"objects\":{\"valueAxis\":[{\"properties\":{\"gridlineShow\":{\"expr\":{\"Literal\":{\"Value\":\"false\"}}},\"showAxisTitle\":{\"expr\":{\"Literal\":{\"Value\":\"false\"}}},\"labelColor\":{\"solid\":{\"color\":{\"expr\":{\"ThemeDataColor\":{\"ColorId\":0,\"Percent\":0}}}}}}}],\"labels\":[{\"properties\":{\"labelPosition\":{\"expr\":{\"Literal\":{\"Value\":\"'InsideEnd'\"}}},\"show\":{\"expr\":{\"Literal\":{\"Value\":\"true\"}}},\"fontFamily\":{\"expr\":{\"Literal\":{\"Value\":\"'''Segoe UI Semibold'', wf_segoe-ui_semibold, helvetica, arial, sans-serif'\"}}}}},{\"properties\":{\"color\":{\"solid\":{\"color\":{\"expr\":{\"ThemeDataColor\":{\"ColorId\":0,\"Percent\":0}}}}}},\"selector\":{\"data\":[{\"dataViewWildcard\":{\"matchingOption\":1}}]}}],\"categoryAxis\":[{\"properties\":{\"show\":{\"expr\":{\"Literal\":{\"Value\":\"true\"}}},\"showAxisTitle\":{\"expr\":{\"Literal\":{\"Value\":\"false\"}}},\"labelColor\":{\"solid\":{\"color\":{\"expr\":{\"ThemeDataColor\":{\"ColorId\":0,\"Percent\":0}}}}},\"fontFamily\":{\"expr\":{\"Literal\":{\"Value\":\"'''Segoe UI Semibold'', wf_segoe-ui_semibold, helvetica, arial, sans-serif'\"}}}}}],\"legend\":[{\"properties\":{\"show\":{\"expr\":{\"Literal\":{\"Value\":\"false\"}}},\"showTitle\":{\"expr\":{\"Literal\":{\"Value\":\"false\"}}},\"labelColor\":{\"solid\":{\"color\":{\"expr\":{\"ThemeDataColor\":{\"ColorId\":0,\"Percent\":0}}}}},\"fontFamily\":{\"expr\":{\"Literal\":{\"Value\":\"'''Segoe UI Semibold'', wf_segoe-ui_semibold, helvetica, arial, sans-serif'\"}}},\"showGradientLegend\":{\"expr\":{\"Literal\":{\"Value\":\"false\"}}}}}],\"dataPoint\":[{\"properties\":{}},{\"properties\":{\"fill\":{\"solid\":{\"color\":{\"expr\":{\"FillRule\":{\"Input\":{\"Measure\":{\"Expression\":{\"SourceRef\":{\"Entity\":\"stolen_vehicles\"}},\"Property\":\"Stolen Vehicles Count\"}},\"FillRule\":{\"linearGradient2\":{\"min\":{\"color\":{\"Literal\":{\"Value\":\"'#B696F6'\"}}},\"max\":{\"color\":{\"Literal\":{\"Value\":\"'#9842ED'\"}}},\"nullColoringStrategy\":{\"strategy\":{\"Literal\":{\"Value\":\"'asZero'\"}}}}}}}}}}},\"selector\":{\"data\":[{\"dataViewWildcard\":{\"matchingOption\":1}}]}}]},\"vcObjects\":{\"title\":[{\"properties\":{\"text\":{\"expr\":{\"Literal\":{\"Value\":\"'Stolen Vehicles by Brand'\"}}},\"titleWrap\":{\"expr\":{\"Literal\":{\"Value\":\"true\"}}},\"fontColor\":{\"solid\":{\"color\":{\"expr\":{\"ThemeDataColor\":{\"ColorId\":0,\"Percent\":0}}}}},\"fontSize\":{\"expr\":{\"Literal\":{\"Value\":\"12D\"}}},\"fontFamily\":{\"expr\":{\"Literal\":{\"Value\":\"'''Segoe UI Semibold'', wf_segoe-ui_semibold, helvetica, arial, sans-serif'\"}}}}}],\"background\":[{\"properties\":{\"show\":{\"expr\":{\"Literal\":{\"Value\":\"false\"}}},\"transparency\":{\"expr\":{\"Literal\":{\"Value\":\"0D\"}}}}}]}}}",
          "filters": "[]",
          "height": 244.71,
          "width": 435.15,
          "x": 528.33,
          "y": 100.34,
          "z": 1000.00
        },
        {
          "config": "{\"name\":\"710ac3ed01b8e5913335\",\"layouts\":[{\"id\":0,\"position\":{\"x\":35.83617747440273,\"y\":100.34129692832764,\"z\":0,\"width\":466.8941979522184,\"height\":244.7098976109215,\"tabOrder\":0}}],\"singleVisual\":{\"visualType\":\"pieChart\",\"projections\":{\"Category\":[{\"queryRef\":\"stolen_vehicles.date_stolen_weekday_text\",\"active\":true}],\"Y\":[{\"queryRef\":\"stolen_vehicles.Stolen Vehicles Count\"}]},\"prototypeQuery\":{\"Version\":2,\"From\":[{\"Name\":\"s\",\"Entity\":\"stolen_vehicles\",\"Type\":0}],\"Select\":[{\"Column\":{\"Expression\":{\"SourceRef\":{\"Source\":\"s\"}},\"Property\":\"date_stolen_weekday_text\"},\"Name\":\"stolen_vehicles.date_stolen_weekday_text\",\"NativeReferenceName\":\"date_stolen_weekday_text\"},{\"Measure\":{\"Expression\":{\"SourceRef\":{\"Source\":\"s\"}},\"Property\":\"Stolen Vehicles Count\"},\"Name\":\"stolen_vehicles.Stolen Vehicles Count\",\"NativeReferenceName\":\"Stolen Vehicles Count\"}],\"OrderBy\":[{\"Direction\":1,\"Expression\":{\"Column\":{\"Expression\":{\"SourceRef\":{\"Source\":\"s\"}},\"Property\":\"date_stolen_weekday_text\"}}}]},\"queryOptions\":{\"keepProjectionOrder\":true},\"showAllRoles\":[\"Category\"],\"drillFilterOtherVisuals\":true,\"objects\":{\"legend\":[{\"properties\":{\"show\":{\"expr\":{\"Literal\":{\"Value\":\"false\"}}},\"showTitle\":{\"expr\":{\"Literal\":{\"Value\":\"false\"}}},\"labelColor\":{\"solid\":{\"color\":{\"expr\":{\"ThemeDataColor\":{\"ColorId\":0,\"Percent\":0}}}}},\"fontFamily\":{\"expr\":{\"Literal\":{\"Value\":\"'''Segoe UI Semibold'', wf_segoe-ui_semibold, helvetica, arial, sans-serif'\"}}}}}],\"labels\":[{\"properties\":{\"labelStyle\":{\"expr\":{\"Literal\":{\"Value\":\"'Both'\"}}},\"show\":{\"expr\":{\"Literal\":{\"Value\":\"true\"}}},\"fontFamily\":{\"expr\":{\"Literal\":{\"Value\":\"'''Segoe UI Semibold'', wf_segoe-ui_semibold, helvetica, arial, sans-serif'\"}}}}},{\"properties\":{\"color\":{\"solid\":{\"color\":{\"expr\":{\"ThemeDataColor\":{\"ColorId\":0,\"Percent\":0}}}}}},\"selector\":{\"data\":[{\"dataViewWildcard\":{\"matchingOption\":1}}]}}],\"dataPoint\":[{\"properties\":{\"fill\":{\"solid\":{\"color\":{\"expr\":{\"ThemeDataColor\":{\"ColorId\":6,\"Percent\":0.6}}}}}},\"selector\":{\"data\":[{\"scopeId\":{\"Comparison\":{\"ComparisonKind\":0,\"Left\":{\"Column\":{\"Expression\":{\"SourceRef\":{\"Entity\":\"stolen_vehicles\"}},\"Property\":\"date_stolen_weekday_text\"}},\"Right\":{\"Literal\":{\"Value\":\"'Monday'\"}}}}}]}},{\"properties\":{\"fill\":{\"solid\":{\"color\":{\"expr\":{\"Literal\":{\"Value\":\"'#D96FFF'\"}}}}}},\"selector\":{\"data\":[{\"scopeId\":{\"Comparison\":{\"ComparisonKind\":0,\"Left\":{\"Column\":{\"Expression\":{\"SourceRef\":{\"Entity\":\"stolen_vehicles\"}},\"Property\":\"date_stolen_weekday_text\"}},\"Right\":{\"Literal\":{\"Value\":\"'Tuesday'\"}}}}}]}},{\"properties\":{\"fill\":{\"solid\":{\"color\":{\"expr\":{\"Literal\":{\"Value\":\"'#A64CFF'\"}}}}}},\"selector\":{\"data\":[{\"scopeId\":{\"Comparison\":{\"ComparisonKind\":0,\"Left\":{\"Column\":{\"Expression\":{\"SourceRef\":{\"Entity\":\"stolen_vehicles\"}},\"Property\":\"date_stolen_weekday_text\"}},\"Right\":{\"Literal\":{\"Value\":\"'Wednesday'\"}}}}}]}},{\"properties\":{\"fill\":{\"solid\":{\"color\":{\"expr\":{\"Literal\":{\"Value\":\"'#744EC2'\"}}}}}},\"selector\":{\"data\":[{\"scopeId\":{\"Comparison\":{\"ComparisonKind\":0,\"Left\":{\"Column\":{\"Expression\":{\"SourceRef\":{\"Entity\":\"stolen_vehicles\"}},\"Property\":\"date_stolen_weekday_text\"}},\"Right\":{\"Literal\":{\"Value\":\"'Sunday'\"}}}}}]}},{\"properties\":{\"fill\":{\"solid\":{\"color\":{\"expr\":{\"Literal\":{\"Value\":\"'#DAB9FB'\"}}}}}},\"selector\":{\"data\":[{\"scopeId\":{\"Comparison\":{\"ComparisonKind\":0,\"Left\":{\"Column\":{\"Expression\":{\"SourceRef\":{\"Entity\":\"stolen_vehicles\"}},\"Property\":\"date_stolen_weekday_text\"}},\"Right\":{\"Literal\":{\"Value\":\"'Friday'\"}}}}}]}},{\"properties\":{\"fill\":{\"solid\":{\"color\":{\"expr\":{\"Literal\":{\"Value\":\"'#C48AFF'\"}}}}}},\"selector\":{\"data\":[{\"scopeId\":{\"Comparison\":{\"ComparisonKind\":0,\"Left\":{\"Column\":{\"Expression\":{\"SourceRef\":{\"Entity\":\"stolen_vehicles\"}},\"Property\":\"date_stolen_weekday_text\"}},\"Right\":{\"Literal\":{\"Value\":\"'Thursday'\"}}}}}]}},{\"properties\":{\"fill\":{\"solid\":{\"color\":{\"expr\":{\"Literal\":{\"Value\":\"'#9279C5'\"}}}}}},\"selector\":{\"data\":[{\"scopeId\":{\"Comparison\":{\"ComparisonKind\":0,\"Left\":{\"Column\":{\"Expression\":{\"SourceRef\":{\"Entity\":\"stolen_vehicles\"}},\"Property\":\"date_stolen_weekday_text\"}},\"Right\":{\"Literal\":{\"Value\":\"'Saturday'\"}}}}}]}}]},\"vcObjects\":{\"title\":[{\"properties\":{\"text\":{\"expr\":{\"Literal\":{\"Value\":\"'Stolen Vehicles by Weekday'\"}}},\"fontColor\":{\"solid\":{\"color\":{\"expr\":{\"ThemeDataColor\":{\"ColorId\":0,\"Percent\":0}}}}},\"fontFamily\":{\"expr\":{\"Literal\":{\"Value\":\"'''Segoe UI Semibold'', wf_segoe-ui_semibold, helvetica, arial, sans-serif'\"}}},\"fontSize\":{\"expr\":{\"Literal\":{\"Value\":\"12D\"}}}}}],\"background\":[{\"properties\":{\"show\":{\"expr\":{\"Literal\":{\"Value\":\"false\"}}}}}]}}}",
          "filters": "[]",
          "height": 244.71,
          "width": 466.89,
          "x": 35.84,
          "y": 100.34,
          "z": 0.00
        },
        {
          "config": "{\"name\":\"9589a9527b419ed41870\",\"layouts\":[{\"id\":0,\"position\":{\"x\":35.83617747440273,\"y\":911.2627986348123,\"z\":5000,\"width\":939.9317406143344,\"height\":252.90102389078498,\"tabOrder\":5000}}],\"singleVisual\":{\"visualType\":\"columnChart\",\"projections\":{\"Category\":[{\"queryRef\":\"locations.region\",\"active\":true}],\"Y\":[{\"queryRef\":\"Sum(locations.population)\"}]},\"prototypeQuery\":{\"Version\":2,\"From\":[{\"Name\":\"l\",\"Entity\":\"locations\",\"Type\":0}],\"Select\":[{\"Column\":{\"Expression\":{\"SourceRef\":{\"Source\":\"l\"}},\"Property\":\"region\"},\"Name\":\"locations.region\",\"NativeReferenceName\":\"region\"},{\"Aggregation\":{\"Expression\":{\"Column\":{\"Expression\":{\"SourceRef\":{\"Source\":\"l\"}},\"Property\":\"population\"}},\"Function\":0},\"Name\":\"Sum(locations.population)\",\"NativeReferenceName\":\"Sum of population\"}],\"OrderBy\":[{\"Direction\":2,\"Expression\":{\"Aggregation\":{\"Expression\":{\"Column\":{\"Expression\":{\"SourceRef\":{\"Source\":\"l\"}},\"Property\":\"population\"}},\"Function\":0}}}]},\"drillFilterOtherVisuals\":true,\"hasDefaultSort\":true,\"objects\":{\"labels\":[{\"properties\":{\"show\":{\"expr\":{\"Literal\":{\"Value\":\"true\"}}},\"labelPosition\":{\"expr\":{\"Literal\":{\"Value\":\"'OutsideEnd'\"}}},\"fontFamily\":{\"expr\":{\"Literal\":{\"Value\":\"'''Segoe UI Semibold'', wf_segoe-ui_semibold, helvetica, arial, sans-serif'\"}}}}},{\"properties\":{\"color\":{\"solid\":{\"color\":{\"expr\":{\"ThemeDataColor\":{\"ColorId\":0,\"Percent\":0}}}}}},\"selector\":{\"data\":[{\"dataViewWildcard\":{\"matchingOption\":1}}]}}],\"legend\":[{\"properties\":{\"show\":{\"expr\":{\"Literal\":{\"Value\":\"false\"}}},\"showTitle\":{\"expr\":{\"Literal\":{\"Value\":\"false\"}}},\"labelColor\":{\"solid\":{\"color\":{\"expr\":{\"ThemeDataColor\":{\"ColorId\":0,\"Percent\":0}}}}},\"fontFamily\":{\"expr\":{\"Literal\":{\"Value\":\"'''Segoe UI Semibold'', wf_segoe-ui_semibold, helvetica, arial, sans-serif'\"}}},\"showGradientLegend\":{\"expr\":{\"Literal\":{\"Value\":\"false\"}}}}}],\"categoryAxis\":[{\"properties\":{\"show\":{\"expr\":{\"Literal\":{\"Value\":\"true\"}}},\"showAxisTitle\":{\"expr\":{\"Literal\":{\"Value\":\"false\"}}},\"labelColor\":{\"solid\":{\"color\":{\"expr\":{\"ThemeDataColor\":{\"ColorId\":0,\"Percent\":0}}}}},\"fontFamily\":{\"expr\":{\"Literal\":{\"Value\":\"'''Segoe UI Semibold'', wf_segoe-ui_semibold, helvetica, arial, sans-serif'\"}}}}}],\"valueAxis\":[{\"properties\":{\"showAxisTitle\":{\"expr\":{\"Literal\":{\"Value\":\"false\"}}},\"labelColor\":{\"solid\":{\"color\":{\"expr\":{\"ThemeDataColor\":{\"ColorId\":0,\"Percent\":0}}}}},\"gridlineShow\":{\"expr\":{\"Literal\":{\"Value\":\"false\"}}},\"show\":{\"expr\":{\"Literal\":{\"Value\":\"false\"}}}}}],\"dataPoint\":[{\"properties\":{\"fill\":{\"solid\":{\"color\":{\"expr\":{\"FillRule\":{\"Input\":{\"Measure\":{\"Expression\":{\"SourceRef\":{\"Entity\":\"stolen_vehicles\"}},\"Property\":\"Stolen Vehicles Count\"}},\"FillRule\":{\"linearGradient2\":{\"min\":{\"color\":{\"Literal\":{\"Value\":\"'#B696F6'\"}}},\"max\":{\"color\":{\"Literal\":{\"Value\":\"'#9842ED'\"}}},\"nullColoringStrategy\":{\"strategy\":{\"Literal\":{\"Value\":\"'asZero'\"}}}}}}}}}}},\"selector\":{\"data\":[{\"dataViewWildcard\":{\"matchingOption\":1}}]}}]},\"vcObjects\":{\"background\":[{\"properties\":{\"show\":{\"expr\":{\"Literal\":{\"Value\":\"false\"}}},\"transparency\":{\"expr\":{\"Literal\":{\"Value\":\"0D\"}}}}}],\"title\":[{\"properties\":{\"titleWrap\":{\"expr\":{\"Literal\":{\"Value\":\"true\"}}},\"fontColor\":{\"solid\":{\"color\":{\"expr\":{\"ThemeDataColor\":{\"ColorId\":0,\"Percent\":0}}}}},\"fontSize\":{\"expr\":{\"Literal\":{\"Value\":\"12D\"}}},\"fontFamily\":{\"expr\":{\"Literal\":{\"Value\":\"'''Segoe UI Semibold'', wf_segoe-ui_semibold, helvetica, arial, sans-serif'\"}}}}}]}}}",
          "filters": "[]",
          "height": 252.90,
          "width": 939.93,
          "x": 35.84,
          "y": 911.26,
          "z": 5000.00
        },
        {
          "config": "{\"name\":\"b71871ac9b0556a01110\",\"layouts\":[{\"id\":0,\"position\":{\"x\":48.122866894197955,\"y\":358.3617747440273,\"z\":2000,\"width\":952.2184300341297,\"height\":228.32764505119454,\"tabOrder\":2000}}],\"singleVisual\":{\"visualType\":\"areaChart\",\"projections\":{\"Category\":[{\"queryRef\":\"stolen_vehicles.model_year\",\"active\":true}],\"Y\":[{\"queryRef\":\"stolen_vehicles.Stolen Vehicles Count\"}]},\"prototypeQuery\":{\"Version\":2,\"From\":[{\"Name\":\"s\",\"Entity\":\"stolen_vehicles\",\"Type\":0}],\"Select\":[{\"Column\":{\"Expression\":{\"SourceRef\":{\"Source\":\"s\"}},\"Property\":\"model_year\"},\"Name\":\"stolen_vehicles.model_year\",\"NativeReferenceName\":\"model_year\"},{\"Measure\":{\"Expression\":{\"SourceRef\":{\"Source\":\"s\"}},\"Property\":\"Stolen Vehicles Count\"},\"Name\":\"stolen_vehicles.Stolen Vehicles Count\",\"NativeReferenceName\":\"Stolen Vehicles Count\"}],\"OrderBy\":[{\"Direction\":2,\"Expression\":{\"Measure\":{\"Expression\":{\"SourceRef\":{\"Source\":\"s\"}},\"Property\":\"Stolen Vehicles Count\"}}}]},\"drillFilterOtherVisuals\":true,\"hasDefaultSort\":true,\"objects\":{\"lineStyles\":[{\"properties\":{\"showMarker\":{\"expr\":{\"Literal\":{\"Value\":\"false\"}}}}}],\"labels\":[{\"properties\":{\"maximumOffset\":{\"expr\":{\"Literal\":{\"Value\":\"30D\"}}},\"minimumOffset\":{\"expr\":{\"Literal\":{\"Value\":\"0D\"}}},\"show\":{\"expr\":{\"Literal\":{\"Value\":\"true\"}}},\"labelPosition\":{\"expr\":{\"Literal\":{\"Value\":\"'InsideEnd'\"}}},\"fontFamily\":{\"expr\":{\"Literal\":{\"Value\":\"'''Segoe UI Semibold'', wf_segoe-ui_semibold, helvetica, arial, sans-serif'\"}}}}},{\"properties\":{\"color\":{\"solid\":{\"color\":{\"expr\":{\"ThemeDataColor\":{\"ColorId\":0,\"Percent\":0}}}}}},\"selector\":{\"data\":[{\"dataViewWildcard\":{\"matchingOption\":1}}]}}],\"valueAxis\":[{\"properties\":{\"showAxisTitle\":{\"expr\":{\"Literal\":{\"Value\":\"false\"}}},\"labelColor\":{\"solid\":{\"color\":{\"expr\":{\"ThemeDataColor\":{\"ColorId\":0,\"Percent\":0}}}}},\"gridlineShow\":{\"expr\":{\"Literal\":{\"Value\":\"false\"}}},\"show\":{\"expr\":{\"Literal\":{\"Value\":\"false\"}}}}}],\"categoryAxis\":[{\"properties\":{\"show\":{\"expr\":{\"Literal\":{\"Value\":\"true\"}}},\"showAxisTitle\":{\"expr\":{\"Literal\":{\"Value\":\"false\"}}},\"labelColor\":{\"solid\":{\"color\":{\"expr\":{\"ThemeDataColor\":{\"ColorId\":0,\"Percent\":0}}}}},\"fontFamily\":{\"expr\":{\"Literal\":{\"Value\":\"'''Segoe UI Semibold'', wf_segoe-ui_semibold, helvetica, arial, sans-serif'\"}}},\"gridlineShow\":{\"expr\":{\"Literal\":{\"Value\":\"false\"}}}}}],\"legend\":[{\"properties\":{\"show\":{\"expr\":{\"Literal\":{\"Value\":\"true\"}}},\"showTitle\":{\"expr\":{\"Literal\":{\"Value\":\"false\"}}},\"labelColor\":{\"solid\":{\"color\":{\"expr\":{\"ThemeDataColor\":{\"ColorId\":0,\"Percent\":0}}}}},\"fontFamily\":{\"expr\":{\"Literal\":{\"Value\":\"'''Segoe UI Semibold'', wf_segoe-ui_semibold, helvetica, arial, sans-serif'\"}}}}}],\"dataPoint\":[{\"properties\":{\"fill\":{\"solid\":{\"color\":{\"expr\":{\"Literal\":{\"Value\":\"'#9842ED'\"}}}}}},\"selector\":{\"metadata\":\"stolen_vehicles.Stolen Vehicles Count\"}}]},\"vcObjects\":{\"title\":[{\"properties\":{\"text\":{\"expr\":{\"Literal\":{\"Value\":\"'Stolen Vehicles by Model Year'\"}}},\"titleWrap\":{\"expr\":{\"Literal\":{\"Value\":\"true\"}}},\"fontColor\":{\"solid\":{\"color\":{\"expr\":{\"ThemeDataColor\":{\"ColorId\":0,\"Percent\":0}}}}},\"fontSize\":{\"expr\":{\"Literal\":{\"Value\":\"12D\"}}},\"fontFamily\":{\"expr\":{\"Literal\":{\"Value\":\"'''Segoe UI Semibold'', wf_segoe-ui_semibold, helvetica, arial, sans-serif'\"}}}}}],\"background\":[{\"properties\":{\"show\":{\"expr\":{\"Literal\":{\"Value\":\"false\"}}},\"transparency\":{\"expr\":{\"Literal\":{\"Value\":\"0D\"}}}}}]}}}",
          "filters": "[]",
          "height": 228.33,
          "width": 952.22,
          "x": 48.12,
          "y": 358.36,
          "z": 2000.00
        },
        {
          "config": "{\"name\":\"d124decaa8280a62e8b8\",\"layouts\":[{\"id\":0,\"position\":{\"x\":528.3276450511945,\"y\":622.5255972696245,\"z\":4000,\"width\":435.1535836177474,\"height\":265.1877133105802,\"tabOrder\":4000}}],\"singleVisual\":{\"visualType\":\"barChart\",\"projections\":{\"Category\":[{\"queryRef\":\"locations.region\",\"active\":true}],\"Y\":[{\"queryRef\":\"stolen_vehicles.Stolen Vehicles Count\"}]},\"prototypeQuery\":{\"Version\":2,\"From\":[{\"Name\":\"s\",\"Entity\":\"stolen_vehicles\",\"Type\":0},{\"Name\":\"l\",\"Entity\":\"locations\",\"Type\":0}],\"Select\":[{\"Column\":{\"Expression\":{\"SourceRef\":{\"Source\":\"l\"}},\"Property\":\"region\"},\"Name\":\"locations.region\",\"NativeReferenceName\":\"region\"},{\"Measure\":{\"Expression\":{\"SourceRef\":{\"Source\":\"s\"}},\"Property\":\"Stolen Vehicles Count\"},\"Name\":\"stolen_vehicles.Stolen Vehicles Count\",\"NativeReferenceName\":\"Stolen Vehicles Count\"}],\"OrderBy\":[{\"Direction\":2,\"Expression\":{\"Measure\":{\"Expression\":{\"SourceRef\":{\"Source\":\"s\"}},\"Property\":\"Stolen Vehicles Count\"}}}]},\"drillFilterOtherVisuals\":true,\"hasDefaultSort\":true,\"objects\":{\"valueAxis\":[{\"properties\":{\"showAxisTitle\":{\"expr\":{\"Literal\":{\"Value\":\"false\"}}},\"labelColor\":{\"solid\":{\"color\":{\"expr\":{\"ThemeDataColor\":{\"ColorId\":0,\"Percent\":0}}}}},\"gridlineShow\":{\"expr\":{\"Literal\":{\"Value\":\"false\"}}}}}],\"categoryAxis\":[{\"properties\":{\"show\":{\"expr\":{\"Literal\":{\"Value\":\"true\"}}},\"showAxisTitle\":{\"expr\":{\"Literal\":{\"Value\":\"false\"}}},\"labelColor\":{\"solid\":{\"color\":{\"expr\":{\"ThemeDataColor\":{\"ColorId\":0,\"Percent\":0}}}}},\"fontFamily\":{\"expr\":{\"Literal\":{\"Value\":\"'''Segoe UI Semibold'', wf_segoe-ui_semibold, helvetica, arial, sans-serif'\"}}}}}],\"labels\":[{\"properties\":{\"show\":{\"expr\":{\"Literal\":{\"Value\":\"true\"}}},\"labelPosition\":{\"expr\":{\"Literal\":{\"Value\":\"'OutsideEnd'\"}}},\"fontFamily\":{\"expr\":{\"Literal\":{\"Value\":\"'''Segoe UI Semibold'', wf_segoe-ui_semibold, helvetica, arial, sans-serif'\"}}}}},{\"properties\":{\"color\":{\"solid\":{\"color\":{\"expr\":{\"ThemeDataColor\":{\"ColorId\":0,\"Percent\":0}}}}}},\"selector\":{\"data\":[{\"dataViewWildcard\":{\"matchingOption\":1}}]}}],\"legend\":[{\"properties\":{\"show\":{\"expr\":{\"Literal\":{\"Value\":\"false\"}}},\"showTitle\":{\"expr\":{\"Literal\":{\"Value\":\"false\"}}},\"labelColor\":{\"solid\":{\"color\":{\"expr\":{\"ThemeDataColor\":{\"ColorId\":0,\"Percent\":0}}}}},\"fontFamily\":{\"expr\":{\"Literal\":{\"Value\":\"'''Segoe UI Semibold'', wf_segoe-ui_semibold, helvetica, arial, sans-serif'\"}}},\"showGradientLegend\":{\"expr\":{\"Literal\":{\"Value\":\"false\"}}}}}],\"dataPoint\":[{\"properties\":{\"fill\":{\"solid\":{\"color\":{\"expr\":{\"FillRule\":{\"Input\":{\"Measure\":{\"Expression\":{\"SourceRef\":{\"Entity\":\"stolen_vehicles\"}},\"Property\":\"Stolen Vehicles Count\"}},\"FillRule\":{\"linearGradient2\":{\"min\":{\"color\":{\"Literal\":{\"Value\":\"'#B696F6'\"}}},\"max\":{\"color\":{\"Literal\":{\"Value\":\"'#9842ED'\"}}},\"nullColoringStrategy\":{\"strategy\":{\"Literal\":{\"Value\":\"'asZero'\"}}}}}}}}}}},\"selector\":{\"data\":[{\"dataViewWildcard\":{\"matchingOption\":1}}]}}]},\"vcObjects\":{\"title\":[{\"properties\":{\"text\":{\"expr\":{\"Literal\":{\"Value\":\"'Stolen Vehicles by Region'\"}}},\"titleWrap\":{\"expr\":{\"Literal\":{\"Value\":\"true\"}}},\"fontColor\":{\"solid\":{\"color\":{\"expr\":{\"ThemeDataColor\":{\"ColorId\":0,\"Percent\":0}}}}},\"fontSize\":{\"expr\":{\"Literal\":{\"Value\":\"12D\"}}},\"fontFamily\":{\"expr\":{\"Literal\":{\"Value\":\"'''Segoe UI Semibold'', wf_segoe-ui_semibold, helvetica, arial, sans-serif'\"}}}}}],\"background\":[{\"properties\":{\"show\":{\"expr\":{\"Literal\":{\"Value\":\"false\"}}},\"transparency\":{\"expr\":{\"Literal\":{\"Value\":\"0D\"}}}}}]}}}",
          "filters": "[]",
          "height": 265.19,
          "width": 435.15,
          "x": 528.33,
          "y": 622.53,
          "z": 4000.00
        }
      ],
      "width": 1000.00
    }
  ]
}